[{"content":"","date":"1 November 2023","permalink":"/my-web/","section":"Juan D.","summary":"","title":"Juan D."},{"content":" A sub-title # Lorem ipsum dolor sit amet, consectetur adipiscing elit. Morbi nibh nisl, vulputate eu lacus vitae, maximus molestie libero. Vestibulum laoreet, odio et sollicitudin sollicitudin, quam ligula tempus urna, sed sagittis eros eros ac felis. In tristique tortor vitae lacinia commodo. Mauris venenatis ultrices purus nec fermentum. Nunc sit amet aliquet metus. Morbi nisl felis, gravida ac consequat vitae, blandit eu libero. Curabitur porta est in dui elementum porttitor. Maecenas fermentum, tortor ac feugiat fringilla, orci sem sagittis massa, a congue risus ipsum vel massa. Aliquam sit amet nunc vulputate, facilisis neque in, faucibus nisl.\n","date":"1 November 2023","permalink":"/my-web/posts/myfirstpost/","section":"Posts","summary":"This is my first post on my site","title":"My first post"},{"content":"","date":"1 November 2023","permalink":"/my-web/posts/","section":"Posts","summary":"","title":"Posts"},{"content":"","date":"1 November 2023","permalink":"/my-web/tags/space/","section":"Tags","summary":"","title":"space"},{"content":"","date":"1 November 2023","permalink":"/my-web/tags/","section":"Tags","summary":"","title":"Tags"},{"content":"","date":"1 January 0001","permalink":"/my-web/authors/","section":"Authors","summary":"","title":"Authors"},{"content":"","date":"1 January 0001","permalink":"/my-web/categories/","section":"Categories","summary":"","title":"Categories"},{"content":"","date":"1 January 0001","permalink":"/my-web/series/","section":"Series","summary":"","title":"Series"}]